{"name":"mod/susie-area","levels":[{"height":0}],"mapWidth":50,"mapHeight":30,"masterLevel":0,"attributes":{"saveMode":"ENABLED","volume":1,"bgm":"rhombusSquare2","cameraInBounds":false,"map-sounds":"CROWD","mapStyle":"rhombus-interior","weather":"NONE","npcRunners":"","area":"fallback"},"screen":{"x":-137,"y":41},"entities":[{"type":"ScalableProp","x":192,"y":416,"level":0,"settings":{"name":"","size":{"x":416,"y":8},"patternOffset":{"x":0,"y":0},"timeOffset":0,"blockNavMap":true,"propConfig":{"sheet":"dungeon-ar","name":"barrierH","ends":null},"spawnCondition":"map.pvpArena","mapId":548}},{"type":"ScalableProp","x":608,"y":152,"level":0,"settings":{"name":"","size":{"x":8,"y":272},"patternOffset":{"x":0,"y":0},"timeOffset":0,"blockNavMap":true,"propConfig":{"sheet":"dungeon-ar","name":"barrierV","ends":{"north":"NORTH_END","south":"SOUTH_END"}},"spawnCondition":"map.pvpArena","mapId":550}},{"type":"ScalableProp","x":284,"y":336,"level":{"level":0,"offset":128},"settings":{"name":"","size":{"x":240,"y":8},"patternOffset":{"x":0,"y":0},"timeOffset":0,"blockNavMap":false,"mapId":791,"propConfig":{"sheet":"dungeon-ar","name":"textPvP","ends":{"west":"STOP","east":"STOP"}},"spawnCondition":"map.pvpSign"}},{"type":"ScalableProp","x":192,"y":152,"level":0,"settings":{"name":"","size":{"x":416,"y":8},"patternOffset":{"x":0,"y":0},"timeOffset":0,"blockNavMap":true,"propConfig":{"sheet":"dungeon-ar","name":"barrierH","ends":null},"spawnCondition":"map.pvpArena","mapId":549}},{"type":"ScalableProp","x":184,"y":152,"level":0,"settings":{"name":"","size":{"x":8,"y":272},"patternOffset":{"x":0,"y":0},"timeOffset":0,"blockNavMap":true,"propConfig":{"sheet":"dungeon-ar","name":"barrierV","ends":{"north":"NORTH_END","south":"SOUTH_END"}},"spawnCondition":"map.pvpArena","mapId":551}},{"type":"Door","x":384,"y":464,"level":0,"settings":{"name":"justDoor","doorType":"DEFAULT","dir":"NORTH","transitionType":"REGULAR","condition":null,"map":"rookie-harbor.inner-info-ug-1","marker":"down","hideCondition":"","blockEventCondition":"","mapId":104,"variation":""}},{"type":"EventTrigger","x":677,"y":192,"level":0,"settings":{"name":"pvpBrake","eventType":"PARALLEL","endCondition":"false","event":[{"type":"IF","withElse":true,"condition":"pvp.lastWinPlayer","thenStep":[{"type":"IF","withElse":false,"condition":"pvp.playerPoints == 1","thenStep":[{"message":{"en_US":"...","de_DE":"...","fr_FR":"...","zh_CN":"...","ja_JP":"...","ko_KR":"..."},"type":"SHOW_SIDE_MSG","person":{"person":"guildac.susie","expression":"DEFAULT"}}]},{"type":"IF","withElse":false,"condition":"pvp.playerPoints == 2","thenStep":[{"message":{"en_US":"Not bad.","de_DE":"Not bad.","fr_FR":"Not bad.","zh_CN":"Not bad.","ja_JP":"Not bad.","ko_KR":"나쁘지 않네."},"type":"SHOW_SIDE_MSG","person":{"person":"guildac.susie","expression":"DEFAULT"}}]},{"type":"IF","withElse":false,"condition":"pvp.playerPoints == 3","thenStep":[{"message":{"en_US":"Impressive huh?","de_DE":"Impressive huh?","fr_FR":"Impressive huh?","zh_CN":"Impressive huh?","ja_JP":"Impressive huh?","ko_KR":"재미있는데?"},"type":"SHOW_SIDE_MSG","person":{"person":"guildac.susie","expression":"DEFAULT"}}]},{"type":"IF","withElse":false,"condition":"pvp.playerPoints == 4","thenStep":[{"message":{"en_US":"It's not over yet!","de_DE":"It's not over yet!","fr_FR":"It's not over yet!","zh_CN":"It's not over yet!","ja_JP":"It's not over yet!","ko_KR":"아직 끝나지 않았어!"},"type":"SHOW_SIDE_MSG","person":{"person":"guildac.susie","expression":"SMILE"}}]}],"elseStep":[{"type":"IF","withElse":false,"condition":"pvp.enemyPoints == 1","thenStep":[{"message":{"en_US":"...","de_DE":"...","fr_FR":"...","zh_CN":"...","ja_JP":"...","ko_KR":"..."},"type":"SHOW_SIDE_MSG","person":{"person":"guildac.susie","expression":"SMUG"}}]},{"type":"IF","withElse":false,"condition":"pvp.enemyPoints == 2","thenStep":[{"message":{"en_US":"That's all?","de_DE":"That's all?","fr_FR":"That's all?","zh_CN":"That's all?","ja_JP":"That's all?","ko_KR":"그게 다인가?"},"type":"SHOW_SIDE_MSG","person":{"person":"guildac.susie","expression":"SMUG"}}]},{"type":"IF","withElse":false,"condition":"pvp.enemyPoints == 3","thenStep":[{"message":{"en_US":"...That's disappointing.","de_DE":"...That's disappointing.","fr_FR":"...That's disappointing.","zh_CN":"...That's disappointing.","ja_JP":"...That's disappointing.","ko_KR":"...실망인데."},"type":"SHOW_SIDE_MSG","person":{"person":"guildac.susie","expression":"SMUG"}}]},{"type":"IF","withElse":false,"condition":"pvp.enemyPoints == 4","thenStep":[{"message":{"en_US":"It's time to end it.","de_DE":"It's time to end it.","fr_FR":"It's time to end it.","zh_CN":"It's time to end it.","ja_JP":"It's time to end it.","ko_KR":"끝낼 시간이군."},"type":"SHOW_SIDE_MSG","person":{"person":"guildac.susie","expression":"SMUG"}}]}]},{"entity":{"player":true},"action":[{"time":-1,"type":"WAIT"}],"repeating":false,"wait":false,"keepState":true,"type":"DO_ACTION"},{"pos":{"x":400,"y":272},"speed":"NORMAL","transition":"EASE_IN_OUT","wait":false,"waitSkip":0,"zoom":1,"type":"SET_CAMERA_POS"},{"ignoreSlowDown":false,"type":"WAIT","time":0.4},{"entity":{"global":true,"name":"Susie"},"stat":"BOTTOM_POS","type":"SET_VAR_ENTITY_STAT","varName":"tmp.pos"},{"entity":{"player":true},"stat":"BOTTOM_POS","type":"SET_VAR_ENTITY_STAT","varName":"tmp.pos2"},{"type":"IF","withElse":true,"condition":"tmp.pos.x < tmp.pos2.x","thenStep":[{"entity":{"player":true},"action":[{"target":{"x":488,"y":272,"lvl":"0"},"maxTime":0,"distance":0,"precise":false,"planOnly":false,"type":"NAVIGATE_TO_POINT"},{"face":"WEST","rotate":true,"rotateSpeed":3,"type":"SET_FACE"},{"time":-1,"type":"WAIT"}],"repeating":false,"wait":false,"keepState":false,"type":"DO_ACTION"},{"entity":{"global":true,"name":"Susie"},"action":[{"value":false,"type":"FACE_TO_TARGET"},{"target":{"x":312,"y":272,"lvl":"0"},"maxTime":0,"distance":0,"precise":false,"planOnly":false,"type":"NAVIGATE_TO_POINT"}],"repeating":false,"wait":true,"keepState":true,"type":"DO_ACTION"}],"elseStep":[{"entity":{"player":true},"action":[{"target":{"x":312,"y":272,"lvl":"0"},"maxTime":0,"distance":0,"precise":false,"planOnly":false,"type":"NAVIGATE_TO_POINT"},{"face":"EAST","rotate":true,"rotateSpeed":3,"type":"SET_FACE"},{"time":-1,"type":"WAIT"}],"repeating":false,"wait":false,"keepState":false,"type":"DO_ACTION"},{"entity":{"global":true,"name":"Susie"},"action":[{"value":false,"type":"FACE_TO_TARGET"},{"target":{"x":488,"y":272,"lvl":"0"},"maxTime":0,"distance":0,"precise":false,"planOnly":false,"type":"NAVIGATE_TO_POINT"}],"repeating":false,"wait":true,"keepState":true,"type":"DO_ACTION"}]},{"autoContinue":false,"type":"PREPARE_PVP_ROUND"},{"entity":{"global":true,"name":"Susie"},"action":[{"entity":{"player":true},"rotate":true,"rotateSpeed":3,"type":"SET_FACE_TO_ENTITY"}],"repeating":true,"wait":false,"keepState":true,"type":"DO_ACTION"},{"ignoreSlowDown":false,"type":"WAIT","time":1},{"entity":{"player":true},"action":[{"time":0,"type":"WAIT"}],"repeating":false,"wait":false,"keepState":false,"type":"DO_ACTION"},{"entity":{"global":true,"name":"Susie"},"action":[{"time":0,"type":"WAIT"}],"repeating":false,"wait":false,"keepState":false,"type":"DO_ACTION"},{"speed":"NORMAL","transition":"EASE_IN_OUT","wait":false,"waitSkip":0,"type":"RESET_CAMERA"},{"type":"START_PVP_ROUND"}],"triggerType":"ALWAYS","mapId":603,"startCondition":"pvp.brake"}},{"type":"EventTrigger","x":676,"y":220,"level":0,"settings":{"name":"pvpEnd","eventType":"CUTSCENE","endCondition":"false","event":[{"entity":{"global":true,"name":"Susie"},"type":"REMOVE_PLAYER_CAMERA_TARGET"},{"mode":"SLOW","type":"PAUSE_BGM"},{"entity":{"global":true,"name":"Susie"},"expCollect":false,"type":"SWAP_BACK_ENEMY_WITH_ENTITY"},{"ignoreSlowDown":false,"type":"WAIT","time":0.1},{"entity":{"global":true,"name":"Susie"},"action":[{"type":"CLEAR_ANIMATION"},{"entity":{"player":true},"rotate":true,"rotateSpeed":3,"type":"SET_FACE_TO_ENTITY"},{"type":"WAIT","time":-1}],"repeating":false,"wait":false,"keepState":false,"immediately":false,"type":"DO_ACTION"},{"type":"DO_INLINE_LEVELUP"},{"pos":{"x":400,"y":272},"speed":"NORMAL","transition":"EASE_IN_OUT","wait":false,"waitSkip":0,"zoom":1,"type":"SET_CAMERA_POS"},{"ignoreSlowDown":false,"type":"WAIT","time":0.1},{"entity":{"player":true},"action":[{"value":"IGNORE","type":"SET_COLL_TYPE"},{"target":{"x":488,"y":272,"lvl":"0"},"maxTime":0,"distance":0,"precise":false,"planOnly":false,"type":"NAVIGATE_TO_POINT"},{"face":"WEST","rotate":true,"rotateSpeed":3,"type":"SET_FACE"}],"repeating":false,"wait":false,"keepState":true,"immediately":false,"type":"DO_ACTION"},{"entity":{"global":true,"name":"Susie"},"action":[{"value":"IGNORE","type":"SET_COLL_TYPE"},{"target":{"x":312,"y":272,"lvl":"0"},"maxTime":0,"distance":0,"precise":false,"planOnly":false,"type":"NAVIGATE_TO_POINT"},{"face":"EAST","rotate":true,"rotateSpeed":3,"type":"SET_FACE"}],"repeating":false,"wait":true,"keepState":true,"immediately":false,"type":"DO_ACTION"},{"ignoreSlowDown":false,"type":"WAIT","time":0.5},{"changeType":"set","type":"CHANGE_VAR_BOOL","varName":"map.pvpSign","value":false},{"changeType":"set","type":"CHANGE_VAR_BOOL","varName":"map.pvpArena","value":false},{"type":"STOP_PVP_BATTLE"},{"ignoreSlowDown":false,"type":"WAIT","time":0.2},{"type":"IF","withElse":true,"condition":"pvp.lastWinPlayer","thenStep":[{"side":"LEFT","order":0,"clearSide":false,"type":"ADD_MSG_PERSON","person":{"person":"guildac.susie","expression":"SMILE"}},{"side":"RIGHT","order":0,"clearSide":false,"type":"ADD_MSG_PERSON","person":{"person":"main.lea","expression":"SMUG"}},{"message":{"en_US":"...","de_DE":"...","fr_FR":"...","zh_CN":"…","ja_JP":"…","ko_KR":"..."},"autoContinue":false,"type":"SHOW_MSG","person":{"person":"guildac.susie","expression":"SMILE"}},{"message":{"en_US":"...!","de_DE":"...!","fr_FR":"...!","zh_CN":"…！","ja_JP":"…！","ko_KR":"...!"},"autoContinue":false,"type":"SHOW_MSG","person":{"person":"main.lea","expression":"PROUD"}},{"message":{"en_US":"It was a good game.","fr_FR":"It was a good game.","zh_CN":"It was a good game.","ja_JP":"It was a good game.","ko_KR":"좋은 승부였다."},"autoContinue":false,"type":"SHOW_MSG","person":{"person":"guildac.susie","expression":"SMILE"}},{"message":{"en_US":"I wish I could have this fun next time.","de_DE":"I wish I could have this fun next time.","fr_FR":"I wish I could have this fun next time.","zh_CN":"I wish I could have this fun next time.","ja_JP":"I wish I could have this fun next time.","ko_KR":"다음에도 이런 재미를 느낄 수 있으면 좋겠군."},"autoContinue":false,"type":"SHOW_MSG","person":{"person":"guildac.susie","expression":"SMILE"}},{"side":"ALL","type":"CLEAR_MSG"}],"elseStep":[{"side":"LEFT","order":0,"clearSide":false,"type":"ADD_MSG_PERSON","person":{"person":"guildac.susie","expression":"SMUG"}},{"side":"RIGHT","order":0,"clearSide":false,"type":"ADD_MSG_PERSON","person":{"person":"main.lea","expression":"EXHAUSTED"}},{"message":{"en_US":"...It's nothing.","de_DE":"...It's nothing.","fr_FR":"...It's nothing.","zh_CN":"...It's nothing.","ja_JP":"...It's nothing.","ko_KR":"...별거 아니네."},"autoContinue":false,"type":"SHOW_MSG","person":{"person":"guildac.susie","expression":"SMUG"}},{"message":{"en_US":"You'd better get stronger and come back.","de_DE":"You'd better get stronger and come back.","fr_FR":"You'd better get stronger and come back.","zh_CN":"You'd better get stronger and come back.","ja_JP":"You'd better get stronger and come back.","ko_KR":"더 강해져서 돌아오는게 좋을거야."},"autoContinue":false,"type":"SHOW_MSG","person":{"person":"guildac.susie","expression":"DEFAULT"}},{"message":{"en_US":"...","de_DE":"...","fr_FR":"...","zh_CN":"…","ja_JP":"…","ko_KR":"..."},"autoContinue":false,"type":"SHOW_MSG","person":{"person":"main.lea","expression":"SAD"}},{"side":"ALL","type":"CLEAR_MSG"}]},{"mode":"IMMEDIATELY","delayed":false,"type":"RESUME_DEFAULT_BGM"},{"type":"RESET_NPC","npc":{"global":true,"name":"Susie"}}],"triggerType":"ALWAYS","mapId":604,"startCondition":"pvp.finished"}},{"type":"NPC","x":392,"y":266,"level":0,"settings":{"name":"Susie","characterName":"guildac.susie","mapId":600,"npcStates":[{"reactType":"FIXED_POS","face":"SOUTH","action":[{"entity":{"player":true},"rotate":true,"rotateSpeed":3,"type":"SET_FACE_TO_ENTITY"}],"hidden":false,"condition":"","config":"normal","event":[{"side":"LEFT","order":0,"clearSide":false,"type":"ADD_MSG_PERSON","person":{"person":"guildac.susie","expression":"DEFAULT"}},{"side":"RIGHT","order":0,"clearSide":false,"type":"ADD_MSG_PERSON","person":{"person":"main.lea","expression":"DETERMINED"}},{"message":{"en_US":"Are you ready for PvP?","de_DE":"Are you ready for PvP?","fr_FR":"Are you ready for PvP?","zh_CN":"Are you ready for PvP?","ja_JP":"Are you ready for PvP?","ko_KR":"PvP 준비는 됐나?"},"autoContinue":false,"type":"SHOW_MSG","person":{"person":"guildac.susie","expression":"DEFAULT"}},{"0":[{"mode":"SLOW","type":"PAUSE_BGM"},{"message":{"en_US":"[nods]","de_DE":"[nickt]","fr_FR":"fr_FR","zh_CN":"[点头]","ja_JP":"[うなずく]","ko_KR":"[끄덕]"},"autoContinue":false,"type":"SHOW_MSG","person":{"person":"main.lea","expression":"NOD"}},{"type":"SET_MSG_EXPRESSION","person":{"person":"main.lea","expression":"DETERMINED"}},{"message":{"en_US":"Alright, let's get started.","de_DE":"Alright, let's get started.","fr_FR":"Alright, let's get started.","zh_CN":"Alright, let's get started.","ja_JP":"Alright, let's get started.","ko_KR":"좋아, 시작해볼까."},"autoContinue":false,"type":"SHOW_MSG","person":{"person":"guildac.susie","expression":"DEFAULT"}},{"side":"ALL","type":"CLEAR_MSG"},{"ignoreSlowDown":false,"type":"WAIT","time":0.4},{"pos":{"x":400,"y":272},"speed":"SLOWER","transition":"EASE_IN_OUT","wait":false,"waitSkip":0,"zoom":1,"type":"SET_CAMERA_POS"},{"entity":{"player":true},"action":[{"time":0.4,"type":"WAIT"},{"target":{"x":488,"y":272,"lvl":"0"},"maxTime":0,"distance":0,"precise":false,"planOnly":false,"type":"NAVIGATE_TO_POINT"},{"face":"WEST","rotate":true,"rotateSpeed":3,"type":"SET_FACE"}],"repeating":false,"wait":false,"keepState":false,"immediately":false,"type":"DO_ACTION"},{"entity":{"global":true,"name":"Susie"},"action":[{"target":{"x":312,"y":272,"lvl":"0"},"maxTime":0,"distance":0,"precise":false,"planOnly":false,"type":"NAVIGATE_TO_POINT"},{"face":"EAST","rotate":true,"rotateSpeed":3,"type":"SET_FACE"}],"repeating":false,"wait":true,"keepState":false,"immediately":false,"type":"DO_ACTION"},{"changeType":"set","type":"CHANGE_VAR_BOOL","varName":"map.pvpSign","value":true},{"ignoreSlowDown":false,"type":"WAIT","time":0.5},{"pos":{"x":400,"y":272},"speed":"FAST","transition":"EASE_IN_OUT","wait":true,"waitSkip":0.3,"zoom":1,"type":"SET_CAMERA_POS"},{"changeType":"set","type":"CHANGE_VAR_BOOL","varName":"map.pvpArena","value":true},{"ignoreSlowDown":false,"type":"WAIT","time":0.6},{"bgm":"shizuka","volume":1,"mode":"IMMEDIATELY","type":"PLAY_BGM"},{"entity":{"global":true,"name":"Susie"},"type":"SWAP_ENTITY_WITH_ENEMY","enemyInfo":{"group":"","party":"","face":"EAST","type":"avatar.susie","level":{"varName":"tmp.susieLevel"},"attribs":{}}},{"entity":{"global":true,"name":"Susie"},"speed":"NORMAL","type":"ADD_PLAYER_CAMERA_TARGET"},{"zoom":1,"duration":1,"transition":"EASE_OUT","type":"SET_CAMERA_ZOOM"},{"winPoints":5,"type":"START_PVP_BATTLE","enemies":[{"global":true,"name":"Susie"}]},{"autoContinue":true,"type":"PREPARE_PVP_ROUND"},{"changeType":"set","type":"CHANGE_VAR_BOOL","varName":"tmp.pvpStarted","value":true}],"1":[{"message":{"en_US":"[shakes head]","de_DE":"[schüttelt Kopf]","fr_FR":"fr_FR","zh_CN":"[摇头]","ja_JP":"[首を振る]","ko_KR":"[도리도리]"},"autoContinue":false,"type":"SHOW_MSG","person":{"person":"main.lea","expression":"SHAKE"}},{"type":"SET_MSG_EXPRESSION","person":{"person":"main.lea","expression":"DETERMINED"}},{"message":{"en_US":"Okay, come back when you're ready.","de_DE":"Okay, come back when you're ready.","fr_FR":"Okay, come back when you're ready.","zh_CN":"Okay, come back when you're ready.","ja_JP":"Okay, come back when you're ready.","ko_KR":"그래, 더 준비하고 와."},"autoContinue":false,"type":"SHOW_MSG","person":{"person":"guildac.susie","expression":"DEFAULT"}}],"type":"SHOW_CHOICE","person":{"person":"main.lea","expression":"DETERMINED"},"options":[{"0":" ","label":{"en_US":"[yes]","de_DE":"[Ja]","fr_FR":"fr_FR","zh_CN":"[是]","ja_JP":"[はい]","ko_KR":"[예]"}},{"0":" ","label":{"en_US":"[no]","de_DE":"[Nein]","fr_FR":"fr_FR","zh_CN":"[否]","ja_JP":"[いいえ]","ko_KR":"[아니요]"}}]}]}]}},{"type":"EventTrigger","x":-6,"y":240,"level":0,"settings":{"name":"levelUp","eventType":"INTERRUPTABLE","endCondition":"false","event":[{"changeType":"add","type":"CHANGE_VAR_NUMBER","varName":"tmp.susieLevel","value":1},{"withElse":false,"type":"IF","condition":"tmp.susieLevel>99","thenStep":[{"changeType":"set","type":"CHANGE_VAR_NUMBER","varName":"tmp.susieLevel","value":99}]},{"entity":{"global":true,"name":"levelUp-switch"},"text":{"en_US":"Level up : \\v[tmp.susieLevel]","de_DE":"Level up : \\v[tmp.susieLevel]","fr_FR":"Level up : \\v[tmp.susieLevel]","zh_CN":"Level up : \\v[tmp.susieLevel]","ja_JP":"Level up : \\v[tmp.susieLevel]","ko_KR":"레벨 업 : \\v[tmp.susieLevel]"},"time":2,"mode":"LINE_FILL","color":"GREEN","type":"SHOW_AR_MSG"}],"triggerType":"ALWAYS","mapId":117,"startCondition":"tmp.levelUp"}},{"type":"OneTimeSwitch","x":16,"y":240,"level":0,"settings":{"name":"levelDown-switch","switchType":"default","activeTime":0.01,"fixCount":0,"variable":"tmp.levelDown","addValue":""}},{"type":"OneTimeSwitch","x":64,"y":240,"level":0,"settings":{"name":"levelUp-switch","switchType":"default","activeTime":0.01,"fixCount":0,"variable":"tmp.levelUp","addValue":""}},{"type":"EventTrigger","x":-6,"y":224,"level":0,"settings":{"name":"mapInit","eventType":"INTERRUPTABLE","endCondition":"false","event":[{"changeType":"set","type":"CHANGE_VAR_NUMBER","varName":"tmp.susieLevel","value":{"varName":"player.level"}},{"type":"CHANGE_VAR_BOOL","changeType":"set","varName":"tmp.hardSp","value":false},{"type":"CHANGE_VAR_BOOL","changeType":"set","varName":"tmp.hardSpMsg","value":false}],"triggerType":"ONCE_PER_ENTRY","mapId":117,"startCondition":"true"}},{"type":"EventTrigger","x":-22,"y":240,"level":0,"settings":{"name":"levelDown","eventType":"INTERRUPTABLE","endCondition":"false","event":[{"changeType":"sub","type":"CHANGE_VAR_NUMBER","varName":"tmp.susieLevel","value":1},{"type":"IF","withElse":false,"condition":"tmp.susieLevel<1","thenStep":[{"changeType":"set","type":"CHANGE_VAR_NUMBER","varName":"tmp.susieLevel","value":1}]},{"type":"SHOW_AR_MSG","entity":{"global":true,"name":"levelDown-switch"},"text":{"en_US":"Level down : \\v[tmp.susieLevel]","de_DE":"Level down : \\v[tmp.susieLevel]","fr_FR":"Level down : \\v[tmp.susieLevel]","zh_CN":"Level down : \\v[tmp.susieLevel]","ja_JP":"Level down : \\v[tmp.susieLevel]","ko_KR":"레벨 다운 : \\v[tmp.susieLevel]"},"time":2,"mode":"LINE_FILL","color":"GREEN"}],"triggerType":"ALWAYS","mapId":117,"startCondition":"tmp.levelDown"}},{"type":"EventTrigger","x":-6,"y":256,"level":0,"settings":{"name":"spHealing","eventType":"INTERRUPTABLE","endCondition":"false","event":[{"type":"RESET_SP","target":{"global":true,"name":"Susie"},"sp":1},{"type":"WAIT","ignoreSlowDown":false,"time":0.2}],"triggerType":"ALWAYS","mapId":99,"startCondition":"map.hardSp"}},{"type":"Prop","x":39,"y":240,"level":{"level":0,"offset":8},"settings":{"name":"hardmodeConsole","interact":{"icon":"INFO","hoverText":{"en_US":"Hardmode Terminal","zh_CN":"Hardmode Terminal","ja_JP":"Hardmode Terminal","ko_KR":"하드모드 단말기","de_DE":"Hardmode Terminal"},"event":[{"side":"RIGHT","order":0,"clearSide":false,"type":"ADD_MSG_PERSON","person":{"person":"main.lea","expression":"DEFAULT"}},{"0":[{"changeType":"set","type":"CHANGE_VAR_BOOL","varName":"map.hardSp","value":true},{"text":{"en_US":"Now Susie's SP will always be full.","de_DE":"Now Susie's SP will always be full.","zh_CN":"Now Susie's SP will always be full.","ja_JP":"Now Susie's SP will always be full.","ko_KR":"이제 수지의 SP가 항상 가득 차게 됩니다."},"center":false,"side":"LEFT","autoContinue":false,"type":"SHOW_BOARD_MSG"}],"1":[{"changeType":"set","type":"CHANGE_VAR_BOOL","varName":"map.hardSp","value":false}],"2":[{"changeType":"set","type":"CHANGE_VAR_BOOL","varName":"map.hardBrake","value":true},{"text":{"en_US":"Now there's no time for her to rest.","de_DE":"Now there's no time for her to rest.","zh_CN":"Now there's no time for her to rest.","ja_JP":"Now there's no time for her to rest.","ko_KR":"이제 그녀에게 휴식시간이란 없습니다."},"center":false,"side":"LEFT","autoContinue":false,"type":"SHOW_BOARD_MSG"}],"3":[{"changeType":"set","type":"CHANGE_VAR_BOOL","varName":"map.hardBrake","value":false}],"4":[],"type":"SHOW_CHOICE","person":{"person":"main.lea","expression":"DEFAULT"},"options":[{"0":" ","label":{"en_US":"\\c[3]Turn on\\c[0] Hardmode: Force","de_DE":"\\c[3]Turn on\\c[0] Hardmode: Force","zh_CN":"\\c[3]Turn on\\c[0] Hardmode: Force","ja_JP":"\\c[3]Turn on\\c[0] Hardmode: Force","ko_KR":"하드모드: 권력 \\c[3]켜기\\c[0]"},"showCondition":"!map.hardSp"},{"0":" ","label":{"en_US":"\\c[2]Turn off\\c[0] Hardmode: Force","de_DE":"\\c[2]Turn off\\c[0] Hardmode: Force","zh_CN":"\\c[2]Turn off\\c[0] Hardmode: Force","ja_JP":"\\c[2]Turn off\\c[0] Hardmode: Force","ko_KR":"하드모드: 권력 \\c[2]끄기\\c[0]"},"showCondition":"map.hardSp"},{"0":" ","label":{"en_US":"\\c[3]Turn on\\c[0] Hardmode: Rage","de_DE":"\\c[3]Turn on\\c[0] Hardmode: Rage","zh_CN":"\\c[3]Turn on\\c[0] Hardmode: Rage","ja_JP":"\\c[3]Turn on\\c[0] Hardmode: Rage","ko_KR":"하드모드: 격노 \\c[3]켜기\\c[0]"},"showCondition":"!map.hardBrake"},{"0":" ","label":{"en_US":"\\c[2]Turn off\\c[0] Hardmode: Rage","de_DE":"\\c[2]Turn off\\c[0] Hardmode: Rage","zh_CN":"\\c[2]Turn off\\c[0] Hardmode: Rage","ja_JP":"\\c[2]Turn off\\c[0] Hardmode: Rage","ko_KR":"하드모드: 격노 \\c[2]끄기\\c[0]"},"showCondition":"map.hardBrake"},{"0":" ","label":{"en_US":"Cancel","de_DE":"Cancel","zh_CN":"Cancel","ja_JP":"Cancel","ko_KR":"취소"}}]}]},"propType":{"sheet":"trading-autumn","name":"signHuge"},"propAnim":"enemy","condAnims":[],"spawnCondition":""}},{"type":"TeleportField","x":133,"y":243,"level":0,"settings":{"name":"drakeTele","dir":"SOUTH","map":"mod.drakeRoom","teleportLabel":{"en_US":"Drake Laser Drill","de_DE":"Drake Laser Drill","zh_CN":"Drake Laser Drill","ja_JP":"Drake Laser Drill","ko_KR":"드레이크 레이저 천공기"},"longTelCond":"false","pseudoExit":false,"gfxType":"AR","mapId":1231,"marker":"goBack","blockEventCondition":"","spawnCondition":"!map.pvpArena"}}],"layer":[{"id":0,"type":"Background","name":"Background","level":0,"width":50,"height":30,"visible":1,"tilesetName":"media/map/rhombus-interior.png","repeat":false,"distance":1,"yDistance":0,"tilesize":16,"moveSpeed":{"x":0,"y":0},"data":[[0,0,0,0,0,0,0,0,0,0,0,0,7,8,8,8,8,8,8,8,8,8,8,8,8,8,8,8,8,8,8,8,8,8,8,8,8,9,0,0,0,0,0,0,0,0,0,0,0,0],[0,0,0,0,0,0,0,0,0,0,0,7,39,16,11,11,11,15,40,16,11,11,11,15,40,40,16,11,11,11,15,40,16,11,11,11,15,41,9,0,0,0,0,0,0,0,0,0,0,0],[0,0,0,0,0,0,0,0,0,0,7,14,71,48,43,43,43,47,72,48,43,43,43,47,72,72,48,43,43,43,47,72,48,43,43,43,47,73,17,9,0,0,0,0,0,0,0,0,0,0],[0,0,0,0,0,0,0,0,0,7,10,46,103,80,75,75,75,79,104,80,75,75,75,79,104,104,80,75,75,75,79,104,80,75,75,75,79,105,49,12,9,0,0,0,0,0,0,0,0,0],[0,0,0,0,0,0,0,0,7,10,42,78,135,112,107,107,107,111,136,112,107,107,107,111,136,136,112,107,107,107,111,136,112,107,107,107,111,137,81,44,12,9,0,0,0,0,0,0,0,0],[0,0,0,0,0,0,0,7,10,42,74,110,167,144,139,139,139,143,168,144,139,139,139,143,168,168,144,139,139,139,143,168,144,139,139,139,143,169,113,76,44,12,9,0,0,0,0,0,0,0],[0,0,0,0,0,0,7,45,42,74,106,142,199,176,171,171,171,175,200,176,171,171,171,175,200,200,176,171,171,171,175,200,176,171,171,171,175,201,145,108,76,44,50,9,0,0,0,0,0,0],[0,0,0,0,0,0,37,77,74,106,138,174,231,1,1,1,1,1,1,1,1,1,1,1,1,1,1,1,1,1,1,1,1,1,1,1,1,233,177,140,108,76,82,38,0,0,0,0,0,0],[0,0,0,0,0,0,37,109,106,138,170,206,1,1,1,1,1,1,1,1,1,1,1,1,1,1,1,1,1,1,1,1,1,1,1,1,1,1,209,172,140,108,114,38,0,0,0,0,0,0],[7,8,8,8,8,9,37,141,138,170,202,1,1,1,1,1,1,1,1,1,1,1,1,1,1,1,1,1,1,1,1,1,1,1,1,1,1,1,1,204,172,140,146,38,0,0,0,0,0,0],[37,11,11,11,11,38,37,173,170,202,1,1,1,1,1,1,1,1,1,1,1,1,1,1,1,1,1,1,1,1,1,1,1,1,1,1,1,1,1,1,204,172,178,38,0,0,0,0,0,0],[37,43,43,43,43,38,37,205,202,1,1,1,1,1,1,1,1,1,1,1,1,1,1,1,1,1,1,1,1,1,1,1,1,1,1,1,1,1,1,1,1,204,210,38,0,0,0,0,0,0],[37,75,75,75,75,38,37,231,1,1,1,1,1,1,1,1,1,1,1,1,1,1,1,1,1,1,1,1,1,1,1,1,1,1,1,1,1,1,1,1,1,1,233,70,0,0,0,0,0,0],[37,107,107,107,107,38,37,1,1,1,1,1,1,1,1,1,1,1,1,1,1,1,1,1,1,1,1,1,1,1,1,1,1,1,1,1,1,1,1,1,1,1,1,0,0,0,0,0,0,0],[37,139,139,139,139,38,37,1,1,1,1,1,1,1,1,1,1,1,1,1,1,1,1,1,583,584,1,1,1,1,1,1,1,1,1,1,1,1,1,1,1,1,1,0,0,0,0,0,0,0],[37,171,171,171,171,12,5,1,1,1,1,1,1,1,1,1,1,1,1,1,1,1,1,583,578,579,584,1,1,1,1,1,1,1,1,1,1,1,1,1,1,1,1,0,0,0,0,0,0,0],[37,1,1,1,1,44,16,1,1,1,1,1,1,1,1,1,1,1,1,1,1,1,583,578,577,577,579,584,1,1,1,1,1,1,1,1,1,1,1,1,1,1,1,0,0,0,0,0,0,0],[37,1,1,1,1,76,48,1,1,1,1,1,1,1,1,1,1,1,1,1,1,1,615,610,577,577,611,616,1,1,1,1,1,1,1,1,1,1,1,1,1,1,1,0,0,0,0,0,0,0],[37,1,1,1,1,108,80,1,1,1,1,1,1,1,1,1,1,1,1,1,1,1,1,615,610,611,616,1,1,1,1,1,1,1,1,1,1,1,1,1,1,1,1,0,0,0,0,0,0,0],[37,1,1,1,1,140,112,1,1,1,1,1,1,1,1,1,1,1,1,1,1,1,1,1,615,616,1,1,1,1,1,1,1,1,1,1,1,1,1,1,1,1,1,0,0,0,0,0,0,0],[37,1,1,1,1,172,144,1,1,1,1,1,1,1,1,1,1,1,1,1,1,1,1,1,1,1,1,1,1,1,1,1,1,1,1,1,1,1,1,1,1,1,1,0,0,0,0,0,0,0],[37,1,1,1,1,204,176,1,1,1,1,1,1,1,1,1,1,1,1,1,1,1,1,1,1,1,1,1,1,1,1,1,1,1,1,1,1,1,1,1,1,1,1,0,0,0,0,0,0,0],[37,1,1,1,1,1,1,1,1,1,1,1,1,1,1,1,1,1,1,1,1,1,1,1,1,1,1,1,1,1,1,1,1,1,1,1,1,1,1,1,1,1,1,0,0,0,0,0,0,0],[37,1,1,1,1,1,1,1,1,1,1,1,1,1,1,1,1,1,1,1,1,1,1,1,1,1,1,1,1,1,1,1,1,1,1,1,1,1,1,1,1,1,1,0,0,0,0,0,0,0],[295,263,1,1,1,1,1,1,1,1,1,1,1,1,1,1,1,1,1,1,1,1,1,1,1,1,1,1,1,1,1,1,1,1,1,1,1,1,1,1,1,1,1,0,0,0,0,0,0,0],[0,295,296,296,296,296,296,263,1,1,1,1,1,1,1,1,1,1,1,1,1,1,1,1,1,1,1,1,1,1,1,1,1,1,1,1,1,1,1,1,1,1,265,0,0,0,0,0,0,0],[0,0,0,0,0,0,0,295,263,1,1,1,1,1,1,1,1,1,1,1,1,1,1,1,1,1,1,1,1,1,1,1,1,1,1,1,1,1,1,1,1,265,297,0,0,0,0,0,0,0],[0,0,0,0,0,0,0,0,295,263,1,1,1,1,1,1,1,1,1,1,1,1,1,1,1,1,1,1,1,1,1,1,1,1,1,1,1,1,1,1,265,297,0,0,0,0,0,0,0,0],[0,0,0,0,0,0,0,0,0,295,263,1,1,1,1,1,1,1,1,1,1,1,1,1,1,1,1,1,1,1,1,1,1,1,1,1,1,1,1,265,297,0,0,0,0,0,0,0,0,0],[0,0,0,0,0,0,0,0,0,0,295,296,296,296,296,296,296,296,296,296,296,296,296,296,296,296,296,296,296,296,296,296,296,296,296,296,296,296,296,297,0,0,0,0,0,0,0,0,0,0]]},{"id":2,"type":"Background","name":"Detail","level":0,"width":50,"height":30,"visible":1,"tilesetName":"media/map/rhombus-interior.png","repeat":false,"distance":1,"yDistance":0,"tilesize":16,"moveSpeed":{"x":0,"y":0},"data":[[0,0,0,0,0,0,0,0,0,0,0,0,0,0,0,0,0,0,0,0,0,0,0,0,0,0,0,0,0,0,0,0,0,0,0,0,0,0,0,0,0,0,0,0,0,0,0,0,0,0],[0,0,0,0,0,0,0,0,0,0,0,0,0,0,0,0,0,0,0,0,0,0,0,0,0,0,0,0,0,0,0,0,0,0,0,0,0,0,0,0,0,0,0,0,0,0,0,0,0,0],[0,0,0,0,0,0,0,0,0,0,0,0,0,0,0,0,0,0,0,0,0,0,0,0,0,0,0,0,0,0,0,0,0,0,0,0,0,0,0,0,0,0,0,0,0,0,0,0,0,0],[0,0,0,0,0,0,0,0,0,0,0,0,0,0,0,0,0,0,0,0,0,0,0,0,0,0,0,0,0,0,0,0,0,0,0,0,0,0,0,0,0,0,0,0,0,0,0,0,0,0],[0,0,0,0,0,0,0,0,0,0,0,0,0,0,0,0,0,0,0,0,0,0,0,0,0,0,0,0,0,0,0,0,0,0,0,0,0,0,0,0,0,0,0,0,0,0,0,0,0,0],[0,0,0,0,0,0,0,0,0,0,0,0,0,0,0,0,0,0,0,0,0,0,0,0,0,0,0,0,0,0,0,0,0,0,0,0,0,0,0,0,0,0,0,0,0,0,0,0,0,0],[0,0,0,0,0,0,0,0,0,0,0,0,0,0,0,0,0,0,0,0,0,0,0,0,0,0,0,0,0,0,0,0,0,0,0,0,0,0,0,0,0,0,0,0,0,0,0,0,0,0],[0,0,0,0,0,0,0,0,0,0,0,0,0,0,0,0,0,0,0,0,0,0,0,0,0,0,0,0,0,0,0,0,0,0,0,0,0,0,0,0,0,0,0,0,0,0,0,0,0,0],[0,0,0,0,0,0,0,0,0,0,0,0,0,0,0,0,0,0,0,0,0,0,0,0,0,0,0,0,0,0,0,0,0,0,0,0,0,0,0,0,0,0,0,0,0,0,0,0,0,0],[0,0,0,0,0,0,0,0,0,0,0,418,386,386,386,386,386,386,386,386,386,386,386,386,386,386,386,386,386,386,386,386,386,386,386,386,386,386,420,0,0,0,0,0,0,0,0,0,0,0],[0,0,0,0,0,0,0,0,0,0,0,449,0,0,0,0,0,0,0,0,0,0,0,0,0,0,0,0,0,0,0,0,0,0,0,0,0,0,449,0,0,0,0,0,0,0,0,0,0,0],[0,0,0,0,0,0,0,0,0,0,0,449,0,0,0,0,0,0,0,0,0,0,0,0,0,0,0,0,0,0,0,0,0,0,0,0,0,0,449,0,0,0,0,0,0,0,0,0,0,0],[0,0,0,0,0,0,0,0,0,0,0,449,0,0,0,0,0,0,0,0,0,0,0,0,0,0,0,0,0,0,0,0,0,0,0,0,0,0,449,0,0,0,0,0,0,0,0,0,0,0],[0,0,0,0,0,0,0,0,0,0,0,449,0,0,0,0,0,0,0,0,0,0,0,0,0,0,0,0,0,0,0,0,0,0,0,0,0,0,449,0,0,0,0,0,0,0,0,0,0,0],[0,0,0,0,0,0,0,0,0,0,0,449,0,0,0,0,0,0,0,0,0,0,0,0,0,0,0,0,0,0,0,0,0,0,0,0,0,0,449,0,0,0,0,0,0,0,0,0,0,0],[0,0,0,0,0,0,0,0,0,0,0,449,0,0,0,0,0,0,0,0,0,0,0,0,0,0,0,0,0,0,0,0,0,0,0,0,0,0,449,0,0,0,0,0,0,0,0,0,0,0],[0,0,0,0,0,0,0,0,0,0,0,449,0,0,0,0,0,0,0,0,0,0,0,0,0,0,0,0,0,0,0,0,0,0,0,0,0,0,449,0,0,0,0,0,0,0,0,0,0,0],[0,0,0,0,0,0,0,0,0,0,0,449,0,0,0,0,0,0,0,0,0,0,0,0,0,0,0,0,0,0,0,0,0,0,0,0,0,0,449,0,0,0,0,0,0,0,0,0,0,0],[0,0,0,0,0,0,0,0,0,0,0,449,0,0,0,0,0,0,0,0,0,0,0,0,0,0,0,0,0,0,0,0,0,0,0,0,0,0,449,0,0,0,0,0,0,0,0,0,0,0],[0,0,0,0,0,0,0,0,0,0,0,449,0,0,0,0,0,0,0,0,0,0,0,0,0,0,0,0,0,0,0,0,0,0,0,0,0,0,449,0,0,0,0,0,0,0,0,0,0,0],[0,0,0,0,0,0,0,0,0,0,0,449,0,0,0,0,0,0,0,0,0,0,0,0,0,0,0,0,0,0,0,0,0,0,0,0,0,0,449,0,0,0,0,0,0,0,0,0,0,0],[0,0,0,0,0,0,0,0,0,0,0,449,0,0,0,0,0,0,0,0,0,0,0,0,0,0,0,0,0,0,0,0,0,0,0,0,0,0,449,0,0,0,0,0,0,0,0,0,0,0],[0,0,0,0,0,0,0,0,0,0,0,449,0,0,0,0,0,0,0,0,0,0,0,0,0,0,0,0,0,0,0,0,0,0,0,0,0,0,449,0,0,0,0,0,0,0,0,0,0,0],[0,0,0,0,0,0,0,0,0,0,0,449,0,0,0,0,0,0,0,0,0,0,0,0,0,0,0,0,0,0,0,0,0,0,0,0,0,0,449,0,0,0,0,0,0,0,0,0,0,0],[0,0,0,0,0,0,0,0,0,0,0,449,0,0,0,0,0,0,0,0,0,0,0,0,0,0,0,0,0,0,0,0,0,0,0,0,0,0,449,0,0,0,0,0,0,0,0,0,0,0],[0,0,0,0,0,0,0,0,0,0,0,449,0,0,0,0,0,0,0,0,0,0,0,0,0,0,0,0,0,0,0,0,0,0,0,0,0,0,449,0,0,0,0,0,0,0,0,0,0,0],[0,0,0,0,0,0,0,0,0,0,0,482,386,386,386,386,386,386,386,386,386,386,386,386,386,386,386,386,386,386,386,386,386,386,386,386,386,386,484,0,0,0,0,0,0,0,0,0,0,0],[0,0,0,0,0,0,0,0,0,0,0,0,0,0,0,0,0,0,0,0,0,0,0,0,0,0,0,0,0,0,0,0,0,0,0,0,0,0,0,0,0,0,0,0,0,0,0,0,0,0],[0,0,0,0,0,0,0,0,0,0,0,0,0,0,0,0,0,0,0,0,0,0,0,0,0,0,0,0,0,0,0,0,0,0,0,0,0,0,0,0,0,0,0,0,0,0,0,0,0,0],[0,0,0,0,0,0,0,0,0,0,0,0,0,0,0,0,0,0,0,0,0,0,0,0,0,0,0,0,0,0,0,0,0,0,0,0,0,0,0,0,0,0,0,0,0,0,0,0,0,0]]},{"id":1,"type":"Background","name":"Objec1","level":"object1","width":50,"height":30,"visible":1,"tilesetName":"media/map/rhombus-interior.png","repeat":false,"distance":1,"yDistance":0,"tilesize":16,"moveSpeed":{"x":0,"y":0},"data":[[0,0,0,0,0,0,0,0,0,0,0,0,0,0,0,0,0,0,0,0,0,0,0,0,0,0,0,0,0,0,0,0,0,0,0,0,0,0,0,0,0,0,0,0,0,0,0,0,0,0],[0,0,0,0,0,0,0,0,0,0,0,0,0,0,0,0,0,0,0,0,0,0,0,0,0,0,0,0,0,0,0,0,0,0,0,0,0,0,0,0,0,0,0,0,0,0,0,0,0,0],[0,0,0,0,0,0,0,0,0,0,0,0,0,0,0,0,0,0,0,0,0,0,0,0,0,0,0,0,0,0,0,0,0,0,0,0,0,0,0,0,0,0,0,0,0,0,0,0,0,0],[0,0,0,0,0,0,0,0,0,0,0,0,0,0,0,0,0,0,0,0,0,0,0,0,0,0,0,0,0,0,0,0,0,0,0,0,0,0,0,0,0,0,0,0,0,0,0,0,0,0],[0,0,0,0,0,0,0,0,0,0,0,0,0,0,0,0,0,0,0,0,0,0,0,0,0,0,0,0,0,0,0,0,0,0,0,0,0,0,0,0,0,0,0,0,0,0,0,0,0,0],[0,0,0,0,0,0,0,0,0,0,0,0,0,0,0,0,0,0,0,0,0,0,0,0,0,0,0,0,0,0,0,0,0,0,0,0,0,0,0,0,0,0,0,0,0,0,0,0,0,0],[0,0,0,0,0,0,0,0,0,0,0,0,0,0,0,0,0,0,0,0,0,0,0,0,0,0,0,0,0,0,0,0,0,0,0,0,0,0,0,0,0,0,0,0,0,0,0,0,0,0],[0,0,0,0,0,0,0,0,0,0,0,0,0,0,0,0,0,0,0,0,0,0,0,0,0,0,0,0,0,0,0,0,0,0,0,0,0,0,0,0,0,0,0,0,0,0,0,0,0,0],[0,0,0,0,0,0,0,0,0,0,0,0,0,0,0,0,0,0,0,0,0,0,0,0,0,0,0,0,0,0,0,0,0,0,0,0,0,0,0,0,0,0,0,0,0,0,0,0,0,0],[0,0,0,0,0,0,0,0,0,0,0,0,0,0,0,0,0,0,0,0,0,0,0,0,0,0,0,0,0,0,0,0,0,0,0,0,0,0,0,0,0,0,0,0,0,0,0,0,0,0],[0,0,0,0,0,0,0,0,0,0,0,0,0,0,0,0,0,0,0,0,0,0,0,0,0,0,0,0,0,0,0,0,0,0,0,0,0,0,0,0,0,0,0,0,0,0,0,0,0,0],[0,0,0,0,0,0,0,0,0,0,0,0,0,0,0,0,0,0,0,0,0,0,0,0,0,0,0,0,0,0,0,0,0,0,0,0,0,0,0,0,0,0,0,0,0,0,0,0,0,0],[0,0,0,0,0,0,0,0,0,0,0,0,0,0,0,0,0,0,0,0,0,0,0,0,0,0,0,0,0,0,0,0,0,0,0,0,0,0,0,0,0,0,0,0,0,0,0,0,0,0],[0,0,0,0,0,0,0,0,0,0,0,0,0,0,0,0,0,0,0,0,0,0,0,0,0,0,0,0,0,0,0,0,0,0,0,0,0,0,0,0,0,0,0,0,0,0,0,0,0,0],[0,0,0,0,0,0,0,0,0,0,0,0,0,0,0,0,0,0,0,0,0,0,0,0,0,0,0,0,0,0,0,0,0,0,0,0,0,0,0,0,0,0,0,0,0,0,0,0,0,0],[0,0,0,0,0,0,0,0,0,0,0,0,0,0,0,0,0,0,0,0,0,0,0,0,0,0,0,0,0,0,0,0,0,0,0,0,0,0,0,0,0,0,0,0,0,0,0,0,0,0],[0,0,0,0,0,0,0,0,0,0,0,0,0,0,0,0,0,0,0,0,0,0,0,0,0,0,0,0,0,0,0,0,0,0,0,0,0,0,0,0,0,0,0,0,0,0,0,0,0,0],[0,0,0,0,0,0,0,0,0,0,0,0,0,0,0,0,0,0,0,0,0,0,0,0,0,0,0,0,0,0,0,0,0,0,0,0,0,0,0,0,0,0,0,0,0,0,0,0,0,0],[0,0,0,0,0,0,0,0,0,0,0,0,0,0,0,0,0,0,0,0,0,0,0,0,0,0,0,0,0,0,0,0,0,0,0,0,0,0,0,0,0,0,0,0,0,0,0,0,0,0],[0,0,0,0,0,0,0,0,0,0,0,0,0,0,0,0,0,0,0,0,0,0,0,0,0,0,0,0,0,0,0,0,0,0,0,0,0,0,0,0,0,0,0,0,0,0,0,0,0,0],[0,0,0,0,0,0,0,0,0,0,0,0,0,0,0,0,0,0,0,0,0,0,0,0,0,0,0,0,0,0,0,0,0,0,0,0,0,0,0,0,0,0,0,0,0,0,0,0,0,0],[0,0,0,0,0,0,0,0,0,0,0,0,0,0,0,0,0,0,0,0,0,0,0,0,0,0,0,0,0,0,0,0,0,0,0,0,0,0,0,0,0,0,0,0,0,0,0,0,0,0],[0,0,0,0,0,0,0,0,0,0,0,0,0,0,0,0,0,0,0,0,0,0,0,0,0,0,0,0,0,0,0,0,0,0,0,0,0,0,0,0,0,0,0,0,0,0,0,0,0,0],[0,0,0,0,0,0,0,0,0,0,0,0,0,0,0,0,0,0,0,0,0,0,0,0,0,0,0,0,0,0,0,0,0,0,0,0,0,0,0,0,0,0,0,0,0,0,0,0,0,0],[0,0,0,0,0,0,0,0,0,0,0,0,0,0,0,0,0,0,0,0,0,0,0,0,0,0,0,0,0,0,0,0,0,0,0,0,0,0,0,0,0,0,0,0,0,0,0,0,0,0],[0,0,0,0,0,0,0,0,0,0,0,0,0,0,0,0,0,0,0,0,0,0,0,0,0,0,0,0,0,0,0,0,0,0,0,0,0,0,0,0,0,0,0,0,0,0,0,0,0,0],[0,0,0,0,0,0,0,0,0,0,0,0,0,0,0,0,0,0,0,0,0,0,0,0,0,0,0,0,0,0,0,0,0,0,0,0,0,0,0,0,0,0,0,0,0,0,0,0,0,0],[0,0,0,0,0,0,0,0,0,0,0,0,0,0,0,0,0,0,0,0,0,0,0,0,0,0,0,0,0,0,0,0,0,0,0,0,0,0,0,0,0,0,0,0,0,0,0,0,0,0],[0,0,0,0,0,0,0,0,0,0,0,0,0,0,0,0,0,0,0,0,0,0,0,0,0,0,0,0,0,0,0,0,0,0,0,0,0,0,0,0,0,0,0,0,0,0,0,0,0,0],[0,0,0,0,0,0,0,0,0,0,0,0,0,0,0,0,0,0,0,0,0,0,0,0,0,0,0,0,0,0,0,0,0,0,0,0,0,0,0,0,0,0,0,0,0,0,0,0,0,0]]},{"type":"Collision","name":"Collision","level":0,"width":50,"height":30,"visible":1,"tilesetName":"media/map/collisiontiles-16x16.png","repeat":false,"distance":1,"tilesize":16,"moveSpeed":{"x":0,"y":0},"data":[[0,0,0,0,0,0,0,0,0,0,0,0,0,0,0,0,0,0,0,0,0,0,0,0,0,0,0,0,0,0,0,0,0,0,0,0,0,0,0,0,0,0,0,0,0,0,0,0,0,0],[0,0,0,0,0,0,0,0,0,0,0,0,0,0,0,0,0,0,0,0,0,0,0,0,0,0,0,0,0,0,0,0,0,0,0,0,0,0,0,0,0,0,0,0,0,0,0,0,0,0],[0,0,0,0,0,0,0,0,0,0,0,0,0,0,0,0,0,0,0,0,0,0,0,0,0,0,0,0,0,0,0,0,0,0,0,0,0,0,0,0,0,0,0,0,0,0,0,0,0,0],[0,0,0,0,0,0,0,0,0,0,0,0,0,0,0,0,0,0,0,0,0,0,0,0,0,0,0,0,0,0,0,0,0,0,0,0,0,0,0,0,0,0,0,0,0,0,0,0,0,0],[0,0,0,0,0,0,0,0,0,0,0,0,0,0,0,0,0,0,0,0,0,0,0,0,0,0,0,0,0,0,0,0,0,0,0,0,0,0,0,0,0,0,0,0,0,0,0,0,0,0],[0,0,0,0,0,2,2,2,2,2,2,2,2,2,2,2,2,2,2,2,2,2,2,2,2,2,2,2,2,2,2,2,2,2,2,2,2,2,2,2,2,2,2,2,0,0,0,0,0,0],[0,0,0,0,0,2,2,2,2,2,2,2,9,0,0,0,0,0,0,0,0,0,0,0,0,0,0,0,0,0,0,0,0,0,0,0,0,10,2,2,2,2,2,2,0,0,0,0,0,0],[0,0,0,0,0,2,2,2,2,2,2,9,0,0,0,0,0,0,0,0,0,0,0,0,0,0,0,0,0,0,0,0,0,0,0,0,0,0,10,2,2,2,2,2,0,0,0,0,0,0],[0,0,0,0,0,2,2,2,2,2,9,0,0,0,0,0,0,0,0,0,0,0,0,0,0,0,0,0,0,0,0,0,0,0,0,0,0,0,0,10,2,2,2,2,0,0,0,0,0,0],[0,0,0,0,0,2,2,2,2,9,0,0,0,0,0,0,0,0,0,0,0,0,0,0,0,0,0,0,0,0,0,0,0,0,0,0,0,0,0,0,10,2,2,2,0,0,0,0,0,0],[0,0,0,0,0,2,2,2,9,0,0,0,0,0,0,0,0,0,0,0,0,0,0,0,0,0,0,0,0,0,0,0,0,0,0,0,0,0,0,0,0,10,2,2,0,0,0,0,0,0],[0,0,0,0,0,2,2,9,0,0,0,0,0,0,0,0,0,0,0,0,0,0,0,0,0,0,0,0,0,0,0,0,0,0,0,0,0,0,0,0,0,0,10,2,0,0,0,0,0,0],[0,0,0,0,0,2,2,0,0,0,0,0,0,0,0,0,0,0,0,0,0,0,0,0,0,0,0,0,0,0,0,0,0,0,0,0,0,0,0,0,0,0,0,2,0,0,0,0,0,0],[0,0,0,0,0,2,2,0,0,0,0,0,0,0,0,0,0,0,0,0,0,0,0,0,0,0,0,0,0,0,0,0,0,0,0,0,0,0,0,0,0,0,0,2,0,0,0,0,0,0],[2,2,2,2,2,2,2,0,0,0,0,0,0,0,0,0,0,0,0,0,0,0,0,0,0,0,0,0,0,0,0,0,0,0,0,0,0,0,0,0,0,0,0,2,0,0,0,0,0,0],[2,0,0,0,0,2,2,0,0,0,0,0,0,0,0,0,0,0,0,0,0,0,0,0,0,0,0,0,0,0,0,0,0,0,0,0,0,0,0,0,0,0,0,2,0,0,0,0,0,0],[2,0,0,0,0,2,2,0,0,0,0,0,0,0,0,0,0,0,0,0,0,0,0,0,0,0,0,0,0,0,0,0,0,0,0,0,0,0,0,0,0,0,0,2,0,0,0,0,0,0],[2,0,0,0,0,2,2,0,0,0,0,0,0,0,0,0,0,0,0,0,0,0,0,0,0,0,0,0,0,0,0,0,0,0,0,0,0,0,0,0,0,0,0,2,0,0,0,0,0,0],[2,0,0,0,0,2,2,0,0,0,0,0,0,0,0,0,0,0,0,0,0,0,0,0,0,0,0,0,0,0,0,0,0,0,0,0,0,0,0,0,0,0,0,2,0,0,0,0,0,0],[2,0,0,0,0,2,2,0,0,0,0,0,0,0,0,0,0,0,0,0,0,0,0,0,0,0,0,0,0,0,0,0,0,0,0,0,0,0,0,0,0,0,0,2,0,0,0,0,0,0],[2,0,0,0,0,10,2,0,0,0,0,0,0,0,0,0,0,0,0,0,0,0,0,0,0,0,0,0,0,0,0,0,0,0,0,0,0,0,0,0,0,0,0,2,0,0,0,0,0,0],[2,0,0,0,0,0,0,0,0,0,0,0,0,0,0,0,0,0,0,0,0,0,0,0,0,0,0,0,0,0,0,0,0,0,0,0,0,0,0,0,0,0,0,2,0,0,0,0,0,0],[2,0,0,0,0,0,0,0,0,0,0,0,0,0,0,0,0,0,0,0,0,0,0,0,0,0,0,0,0,0,0,0,0,0,0,0,0,0,0,0,0,0,0,2,0,0,0,0,0,0],[2,0,0,0,0,0,0,0,0,0,0,0,0,0,0,0,0,0,0,0,0,0,0,0,0,0,0,0,0,0,0,0,0,0,0,0,0,0,0,0,0,0,0,2,0,0,0,0,0,0],[2,8,0,0,0,0,0,0,0,0,0,0,0,0,0,0,0,0,0,0,0,0,0,0,0,0,0,0,0,0,0,0,0,0,0,0,0,0,0,0,0,0,0,2,0,0,0,0,0,0],[2,2,2,2,2,2,2,8,0,0,0,0,0,0,0,0,0,0,0,0,0,0,0,0,0,0,0,0,0,0,0,0,0,0,0,0,0,0,0,0,0,0,11,2,0,0,0,0,0,0],[0,0,0,0,0,0,2,2,8,0,0,0,0,0,0,0,0,0,0,0,0,0,0,0,0,0,0,0,0,0,0,0,0,0,0,0,0,0,0,0,0,11,2,2,0,0,0,0,0,0],[0,0,0,0,0,0,2,2,2,8,0,0,0,0,0,0,0,0,0,0,0,0,0,0,0,0,0,0,0,0,0,0,0,0,0,0,0,0,0,0,11,2,2,2,0,0,0,0,0,0],[0,0,0,0,0,0,2,2,2,2,8,0,0,0,0,0,0,0,0,0,0,0,0,0,0,0,0,0,0,0,0,0,0,0,0,0,0,0,0,11,2,2,2,2,0,0,0,0,0,0],[0,0,0,0,0,0,2,2,2,2,2,2,2,2,2,2,2,2,2,2,2,2,2,2,2,2,2,2,2,2,2,2,2,2,2,2,2,2,2,2,2,2,2,2,0,0,0,0,0,0]]},{"type":"Navigation","name":"Navigation","level":0,"width":50,"height":30,"visible":1,"tilesetName":"media/map/pathmap-tiles.png","repeat":false,"distance":1,"tilesize":16,"moveSpeed":{"x":0,"y":0},"data":[[0,0,0,0,0,0,0,0,0,0,0,0,0,0,0,0,0,0,0,0,0,0,0,0,0,0,0,0,0,0,0,0,0,0,0,0,0,0,0,0,0,0,0,0,0,0,0,0,0,0],[0,0,0,0,0,0,0,0,0,0,0,0,0,0,0,0,0,0,0,0,0,0,0,0,0,0,0,0,0,0,0,0,0,0,0,0,0,0,0,0,0,0,0,0,0,0,0,0,0,0],[0,0,0,0,0,0,0,0,0,0,0,0,0,0,0,0,0,0,0,0,0,0,0,0,0,0,0,0,0,0,0,0,0,0,0,0,0,0,0,0,0,0,0,0,0,0,0,0,0,0],[0,0,0,0,0,0,0,0,0,0,0,0,0,0,0,0,0,0,0,0,0,0,0,0,0,0,0,0,0,0,0,0,0,0,0,0,0,0,0,0,0,0,0,0,0,0,0,0,0,0],[0,0,0,0,0,0,0,0,0,0,0,0,0,0,0,0,0,0,0,0,0,0,0,0,0,0,0,0,0,0,0,0,0,0,0,0,0,0,0,0,0,0,0,0,0,0,0,0,0,0],[0,0,0,0,0,0,0,0,0,0,0,0,0,0,0,0,0,0,0,0,0,0,0,0,0,0,0,0,0,0,0,0,0,0,0,0,0,0,0,0,0,0,0,0,0,0,0,0,0,0],[0,0,0,0,0,0,0,0,0,0,0,0,0,2,2,2,3,3,3,3,3,3,3,3,3,3,3,3,3,3,3,3,3,3,2,2,2,0,0,0,0,0,0,0,0,0,0,0,0,0],[0,0,0,0,0,0,0,0,0,0,0,0,2,2,2,2,3,3,3,3,3,3,3,3,3,3,3,3,3,3,3,3,3,3,2,2,2,2,0,0,0,0,0,0,0,0,0,0,0,0],[0,0,0,0,0,0,0,0,0,0,0,2,2,2,2,2,3,3,3,3,3,3,3,3,3,3,3,3,3,3,3,3,3,3,2,2,2,2,2,0,0,0,0,0,0,0,0,0,0,0],[0,0,0,0,0,0,0,0,0,0,2,2,2,2,2,2,3,3,3,3,3,3,3,3,3,3,3,3,3,3,3,3,3,3,2,2,2,2,2,2,0,0,0,0,0,0,0,0,0,0],[0,0,0,0,0,0,0,0,0,3,3,1,1,1,1,1,1,1,1,1,1,1,1,1,1,1,1,1,1,1,1,1,1,1,1,1,1,1,1,3,3,3,0,0,0,0,0,0,0,0],[0,0,0,0,0,0,0,0,3,3,3,1,1,1,1,1,1,1,1,1,1,1,1,1,1,1,1,1,1,1,1,1,1,1,1,1,1,1,1,3,3,3,3,0,0,0,0,0,0,0],[0,0,0,0,0,0,0,3,3,3,3,1,1,1,1,1,1,1,1,1,1,1,1,1,1,1,1,1,1,1,1,1,1,1,1,1,1,1,1,3,3,3,3,0,0,0,0,0,0,0],[0,0,0,0,0,0,0,3,3,3,3,1,1,1,1,1,1,1,1,1,1,1,1,1,1,1,1,1,1,1,1,1,1,1,1,1,1,1,1,3,3,3,3,0,0,0,0,0,0,0],[0,0,0,0,0,0,0,3,3,3,3,1,1,1,1,1,1,1,1,1,1,1,1,1,1,1,1,1,1,1,1,1,1,1,1,1,1,1,1,3,3,3,3,0,0,0,0,0,0,0],[0,2,2,2,2,0,0,3,3,3,3,1,1,1,1,1,1,1,1,1,1,1,1,1,1,1,1,1,1,1,1,1,1,1,1,1,1,1,1,3,3,3,3,0,0,0,0,0,0,0],[0,2,2,2,2,0,0,3,3,3,3,1,1,1,1,1,1,1,1,1,1,1,1,1,1,1,1,1,1,1,1,1,1,1,1,1,1,1,1,3,3,3,3,0,0,0,0,0,0,0],[0,2,2,2,2,0,0,3,3,3,3,1,1,1,1,1,1,1,1,1,1,1,1,1,1,1,1,1,1,1,1,1,1,1,1,1,1,1,1,3,3,3,3,0,0,0,0,0,0,0],[0,2,2,2,2,0,0,3,3,3,3,1,1,1,1,1,1,1,1,1,1,1,1,1,1,1,1,1,1,1,1,1,1,1,1,1,1,1,1,3,3,3,3,0,0,0,0,0,0,0],[0,2,2,2,2,0,0,3,3,3,3,1,1,1,1,1,1,1,1,1,1,1,1,1,1,1,1,1,1,1,1,1,1,1,1,1,1,1,1,3,3,3,3,0,0,0,0,0,0,0],[0,2,2,2,2,0,0,3,3,3,3,1,1,1,1,1,1,1,1,1,1,1,1,1,1,1,1,1,1,1,1,1,1,1,1,1,1,1,1,3,3,3,3,0,0,0,0,0,0,0],[0,2,2,2,2,2,2,3,3,3,3,1,1,1,1,1,1,1,1,1,1,1,1,1,1,1,1,1,1,1,1,1,1,1,1,1,1,1,1,3,3,3,3,0,0,0,0,0,0,0],[0,2,2,2,2,2,2,3,3,3,3,1,1,1,1,1,1,1,1,1,1,1,1,1,1,1,1,1,1,1,1,1,1,1,1,1,1,1,1,3,3,3,3,0,0,0,0,0,0,0],[0,2,2,2,2,2,2,3,3,3,3,1,1,1,1,1,1,1,1,1,1,1,1,1,1,1,1,1,1,1,1,1,1,1,1,1,1,1,1,3,3,3,3,0,0,0,0,0,0,0],[0,0,2,2,2,2,2,3,3,3,3,1,1,1,1,1,1,1,1,1,1,1,1,1,1,1,1,1,1,1,1,1,1,1,1,1,1,1,1,3,3,3,3,0,0,0,0,0,0,0],[0,0,0,0,0,0,0,0,3,3,3,1,1,1,1,1,1,1,1,1,1,1,1,1,1,1,1,1,1,1,1,1,1,1,1,1,1,1,1,3,3,3,0,0,0,0,0,0,0,0],[0,0,0,0,0,0,0,0,0,3,3,2,2,2,2,2,4,4,4,4,4,4,4,4,4,4,4,4,4,4,4,4,4,4,2,2,2,2,2,3,3,0,0,0,0,0,0,0,0,0],[0,0,0,0,0,0,0,0,0,0,2,2,2,2,2,2,4,4,4,4,4,4,4,4,4,4,4,4,4,4,4,4,4,4,2,2,2,2,2,2,0,0,0,0,0,0,0,0,0,0],[0,0,0,0,0,0,0,0,0,0,0,2,2,2,2,2,4,4,4,4,4,4,4,4,4,4,4,4,4,4,4,4,4,4,2,2,2,2,2,0,0,0,0,0,0,0,0,0,0,0],[0,0,0,0,0,0,0,0,0,0,0,0,0,0,0,0,0,0,0,0,0,0,0,0,0,0,0,0,0,0,0,0,0,0,0,0,0,0,0,0,0,0,0,0,0,0,0,0,0,0]]}]}